dt_ssh_copy_id.py
dt_ssh_copy_id-0.1.0.dist-info/entry_points.txt
dt_ssh_copy_id-0.1.0.dist-info/LICENSE
dt_ssh_copy_id-0.1.0.dist-info/METADATA
dt_ssh_copy_id-0.1.0.dist-info/WHEEL
dt_ssh_copy_id-0.1.0.dist-info/RECORD
