Metadata-Version: 2.3
Name: dt-ssh-copy-id
Version: 0.1.0
Summary: Windows ssh-copy-id utility.
License: MIT
Keywords: python,ssh,CLI,command-line,ssh-copy-id
Author: Al D'Amico
Author-email: JavaWiz1@hotmail.com
Requires-Python: >=3.10,<4.0.0
Classifier: License :: OSI Approved :: MIT License
Classifier: Programming Language :: Python :: 3
Classifier: Programming Language :: Python :: 3.10
Classifier: Programming Language :: Python :: 3.11
Classifier: Programming Language :: Python :: 3.12
Classifier: Programming Language :: Python :: 3.13
Requires-Dist: fabric (>=3.2.2,<4.0.0)
Requires-Dist: loguru (>=0.7.3,<0.8.0)
